[
    {
        "request_body": {
            "store_id": "6A2FE030-08F8-44E0-842F-1D92A0874096",
            "client_id": "02B8E29F-7475-436F-94AA-D631E3577A28",
            "request_id": "58d54193-6185-4c80-b09d-5847a110c0d4",
            "request_payload": {
                "is_closed": true,
                "is_voided": false,
                "channel": "MOBILE",
                "pos_employee_id": "234234",
                "transaction_id": "d22b9215-3fbc-4eea-979b-d57905379d8c",
                "guest_count": 1,
                "subtotal": 49.0,
                "tax_total": 0.0,
                "open_time": "2024-06-25T15:25:49.589Z",
                "modified_time": "2024-06-25T15:25:49.589Z",
                "items": [
                    {
                        "line_id": "1",
                        "item_id": "008884303989M",
                        "quantity": 1,
                        "unit_price": 49.0,
                        "subtotal": 49.0,
                        "tax_included": 0
                    }
                ],
                "payments": [
                    {
                        "payment_id": "96cf3c2b-849f-4d10-9afe-16485c9a6cb2",
                        "amount": 49.0,
                        "type": "Cash",
                        "payment_time": "2024-06-25T15:25:49.589Z",
                        "user_id": "32c61170-3307-11ef-940f-a7c7ac110004",
                        "user_id_type": "External_ID"
                    }
                ],
                "discounts": [],
                "transaction_type": "QSR_SALE"
            }
        },
        "status": 200,
        "response": "{\"status\":\"OK\",\"payload\":null,\"errors\":null}"
    },
    {
        "request_body": {
            "store_id": "6A2FE030-08F8-44E0-842F-1D92A0874096",
            "client_id": "02B8E29F-7475-436F-94AA-D631E3577A28",
            "request_id": "c5e85aad-00ef-422c-b02a-1ef29499dfe0",
            "request_payload": {
                "is_closed": true,
                "is_voided": false,
                "channel": "IN-STORE",
                "pos_employee_id": "234234",
                "transaction_id": "5a623666-2af6-4ed3-993e-54ebd9f7a836",
                "guest_count": 1,
                "subtotal": 50.0,
                "tax_total": 0.0,
                "open_time": "2024-06-25T15:25:49.589Z",
                "modified_time": "2024-06-25T15:25:49.589Z",
                "items": [
                    {
                        "line_id": "1",
                        "item_id": "008884303989M",
                        "quantity": 1,
                        "unit_price": 50.0,
                        "subtotal": 50.0,
                        "tax_included": 0
                    }
                ],
                "payments": [
                    {
                        "payment_id": "99ef78fc-6f1a-4fca-b7a3-fdcec5635d50",
                        "amount": 50.0,
                        "type": "Cash",
                        "payment_time": "2024-06-25T15:25:49.589Z",
                        "user_id": "32c629da-3307-11ef-96e9-aedcac110005",
                        "user_id_type": "External_ID"
                    }
                ],
                "discounts": [],
                "transaction_type": "QSR_SALE"
            }
        },
        "status": 200,
        "response": "{\"status\":\"OK\",\"payload\":null,\"errors\":null}"
    },
    {
        "request_body": {
            "store_id": "6A2FE030-08F8-44E0-842F-1D92A0874096",
            "client_id": "02B8E29F-7475-436F-94AA-D631E3577A28",
            "request_id": "3b5700d8-5236-47f6-95a9-2c8519399aa7",
            "request_payload": {
                "is_closed": true,
                "is_voided": false,
                "channel": "IN-STORE",
                "pos_employee_id": "234234",
                "transaction_id": "c7dd1137-7878-4bfa-9c8f-bfdcbba42ba1",
                "guest_count": 1,
                "subtotal": 98.0,
                "tax_total": 0.0,
                "open_time": "2024-06-25T15:25:49.589Z",
                "modified_time": "2024-06-25T15:25:49.589Z",
                "items": [
                    {
                        "line_id": "1",
                        "item_id": "008884303989M",
                        "quantity": 1,
                        "unit_price": 98.0,
                        "subtotal": 98.0,
                        "tax_included": 0
                    }
                ],
                "payments": [
                    {
                        "payment_id": "03a7d486-fe8a-4059-b662-834236619905",
                        "amount": 98.0,
                        "type": "Gift Card",
                        "payment_time": "2024-06-25T15:25:49.589Z",
                        "user_id": "32c6f8b0-3307-11ef-9b00-882eac110003",
                        "user_id_type": "External_ID"
                    }
                ],
                "discounts": [],
                "transaction_type": "QSR_SALE"
            }
        },
        "status": 200,
        "response": "{\"status\":\"OK\",\"payload\":null,\"errors\":null}"
    },
    {
        "request_body": {
            "store_id": "6A2FE030-08F8-44E0-842F-1D92A0874096",
            "client_id": "02B8E29F-7475-436F-94AA-D631E3577A28",
            "request_id": "30530765-41bc-4849-a05c-dab2fe1532ec",
            "request_payload": {
                "is_closed": true,
                "is_voided": false,
                "channel": "IN-STORE",
                "pos_employee_id": "234234",
                "transaction_id": "3236afa0-7e33-4306-a68a-90562e3677c0",
                "guest_count": 1,
                "subtotal": 30.0,
                "tax_total": 0.0,
                "open_time": "2024-06-25T15:25:49.589Z",
                "modified_time": "2024-06-25T15:25:49.589Z",
                "items": [
                    {
                        "line_id": "1",
                        "item_id": "008884303989M",
                        "quantity": 1,
                        "unit_price": 30.0,
                        "subtotal": 30.0,
                        "tax_included": 0
                    }
                ],
                "payments": [
                    {
                        "payment_id": "70edd8e9-09fc-4490-815d-05a40844c8db",
                        "amount": 30.0,
                        "type": "Gift Card",
                        "payment_time": "2024-06-25T15:25:49.589Z",
                        "user_id": "32c7100c-3307-11ef-8c8e-120cac110003",
                        "user_id_type": "External_ID"
                    }
                ],
                "discounts": [],
                "transaction_type": "QSR_SALE"
            }
        },
        "status": 200,
        "response": "{\"status\":\"OK\",\"payload\":null,\"errors\":null}"
    },
    {
        "request_body": {
            "store_id": "6A2FE030-08F8-44E0-842F-1D92A0874096",
            "client_id": "02B8E29F-7475-436F-94AA-D631E3577A28",
            "request_id": "74497e0a-ac0d-4306-b367-f59005de3c38",
            "request_payload": {
                "is_closed": true,
                "is_voided": false,
                "channel": "IN-STORE",
                "pos_employee_id": "234234",
                "transaction_id": "a786b84e-d673-44f2-b9d4-f7c4d9d81be0",
                "guest_count": 1,
                "subtotal": 85.0,
                "tax_total": 0.0,
                "open_time": "2024-06-25T15:25:49.589Z",
                "modified_time": "2024-06-25T15:25:49.589Z",
                "items": [
                    {
                        "line_id": "1",
                        "item_id": "008884303989M",
                        "quantity": 1,
                        "unit_price": 85.0,
                        "subtotal": 85.0,
                        "tax_included": 0
                    }
                ],
                "payments": [
                    {
                        "payment_id": "548edf5a-cd52-4d7b-a441-30bb77d4b142",
                        "amount": 85.0,
                        "type": "Credit",
                        "payment_time": "2024-06-25T15:25:49.589Z",
                        "user_id": "32c46078-3307-11ef-9472-28bbac110003",
                        "user_id_type": "External_ID"
                    }
                ],
                "discounts": [],
                "transaction_type": "QSR_SALE"
            }
        },
        "status": 200,
        "response": "{\"status\":\"OK\",\"payload\":null,\"errors\":null}"
    },
    {
        "request_body": {
            "store_id": "6A2FE030-08F8-44E0-842F-1D92A0874096",
            "client_id": "02B8E29F-7475-436F-94AA-D631E3577A28",
            "request_id": "6b287c3a-076b-49f8-a1c8-b2304d6a8391",
            "request_payload": {
                "is_closed": true,
                "is_voided": false,
                "channel": "IN-STORE",
                "pos_employee_id": "234234",
                "transaction_id": "7cdec914-f222-48d3-9fc6-299c6e0be6f7",
                "guest_count": 1,
                "subtotal": 56.0,
                "tax_total": 0.0,
                "open_time": "2024-06-25T15:25:49.589Z",
                "modified_time": "2024-06-25T15:25:49.589Z",
                "items": [
                    {
                        "line_id": "1",
                        "item_id": "008884303989M",
                        "quantity": 1,
                        "unit_price": 56.0,
                        "subtotal": 56.0,
                        "tax_included": 0
                    }
                ],
                "payments": [
                    {
                        "payment_id": "e344c400-e388-4724-ae33-01d0555d3865",
                        "amount": 56.0,
                        "type": "Gift Card",
                        "payment_time": "2024-06-25T15:25:49.589Z",
                        "user_id": "32c0cda0-3307-11ef-8161-cc34ac110004",
                        "user_id_type": "External_ID"
                    }
                ],
                "discounts": [],
                "transaction_type": "QSR_SALE"
            }
        },
        "status": 200,
        "response": "{\"status\":\"OK\",\"payload\":null,\"errors\":null}"
    },
    {
        "request_body": {
            "store_id": "6A2FE030-08F8-44E0-842F-1D92A0874096",
            "client_id": "02B8E29F-7475-436F-94AA-D631E3577A28",
            "request_id": "60a75b97-a292-4e18-a52c-96043220d73a",
            "request_payload": {
                "is_closed": true,
                "is_voided": false,
                "channel": "MOBILE",
                "pos_employee_id": "234234",
                "transaction_id": "9227c851-ea88-4398-9c4f-979d4be2d2ca",
                "guest_count": 1,
                "subtotal": 31.0,
                "tax_total": 0.0,
                "open_time": "2024-06-25T15:25:49.589Z",
                "modified_time": "2024-06-25T15:25:49.589Z",
                "items": [
                    {
                        "line_id": "1",
                        "item_id": "008884303989M",
                        "quantity": 1,
                        "unit_price": 31.0,
                        "subtotal": 31.0,
                        "tax_included": 0
                    }
                ],
                "payments": [
                    {
                        "payment_id": "3155628e-7077-4d7f-8be9-90557407afae",
                        "amount": 31.0,
                        "type": "Cash",
                        "payment_time": "2024-06-25T15:25:49.589Z",
                        "user_id": "32c3b07e-3307-11ef-8932-eb11ac110003",
                        "user_id_type": "External_ID"
                    }
                ],
                "discounts": [],
                "transaction_type": "QSR_SALE"
            }
        },
        "status": 200,
        "response": "{\"status\":\"OK\",\"payload\":null,\"errors\":null}"
    },
    {
        "request_body": {
            "store_id": "6A2FE030-08F8-44E0-842F-1D92A0874096",
            "client_id": "02B8E29F-7475-436F-94AA-D631E3577A28",
            "request_id": "335fbe65-851e-4183-9683-ee2db4a5b79d",
            "request_payload": {
                "is_closed": true,
                "is_voided": false,
                "channel": "IN-STORE",
                "pos_employee_id": "234234",
                "transaction_id": "e946d6b0-1c0b-477c-b5c4-ce274c6f634d",
                "guest_count": 1,
                "subtotal": 24.0,
                "tax_total": 0.0,
                "open_time": "2024-06-25T15:25:49.589Z",
                "modified_time": "2024-06-25T15:25:49.589Z",
                "items": [
                    {
                        "line_id": "1",
                        "item_id": "008884303989M",
                        "quantity": 1,
                        "unit_price": 24.0,
                        "subtotal": 24.0,
                        "tax_included": 0
                    }
                ],
                "payments": [
                    {
                        "payment_id": "33f284a3-973f-4d85-9845-3da05ec1a958",
                        "amount": 24.0,
                        "type": "Gift Card",
                        "payment_time": "2024-06-25T15:25:49.589Z",
                        "user_id": "32c5ebe6-3307-11ef-9aad-aedaac110005",
                        "user_id_type": "External_ID"
                    }
                ],
                "discounts": [],
                "transaction_type": "QSR_SALE"
            }
        },
        "status": 200,
        "response": "{\"status\":\"OK\",\"payload\":null,\"errors\":null}"
    },
    {
        "request_body": {
            "store_id": "6A2FE030-08F8-44E0-842F-1D92A0874096",
            "client_id": "02B8E29F-7475-436F-94AA-D631E3577A28",
            "request_id": "804d2842-510f-4451-8924-4bcb4b0b0858",
            "request_payload": {
                "is_closed": true,
                "is_voided": false,
                "channel": "IN-STORE",
                "pos_employee_id": "234234",
                "transaction_id": "58c6b17f-0d46-4a84-9eec-55d0599af97b",
                "guest_count": 1,
                "subtotal": 73.0,
                "tax_total": 0.0,
                "open_time": "2024-06-25T15:25:49.589Z",
                "modified_time": "2024-06-25T15:25:49.589Z",
                "items": [
                    {
                        "line_id": "1",
                        "item_id": "008884303989M",
                        "quantity": 1,
                        "unit_price": 73.0,
                        "subtotal": 73.0,
                        "tax_included": 0
                    }
                ],
                "payments": [
                    {
                        "payment_id": "f4c1d74a-b415-4326-a67b-1dc9572d6bf1",
                        "amount": 73.0,
                        "type": "Cash",
                        "payment_time": "2024-06-25T15:25:49.589Z",
                        "user_id": "32c56a2c-3307-11ef-8c78-d385ac110003",
                        "user_id_type": "External_ID"
                    }
                ],
                "discounts": [],
                "transaction_type": "QSR_SALE"
            }
        },
        "status": 200,
        "response": "{\"status\":\"OK\",\"payload\":null,\"errors\":null}"
    },
    {
        "request_body": {
            "store_id": "6A2FE030-08F8-44E0-842F-1D92A0874096",
            "client_id": "02B8E29F-7475-436F-94AA-D631E3577A28",
            "request_id": "fdfd1631-96fe-41ac-a674-60bf3d92e48f",
            "request_payload": {
                "is_closed": true,
                "is_voided": false,
                "channel": "IN-STORE",
                "pos_employee_id": "234234",
                "transaction_id": "071bc7c2-d2d7-41b4-b020-570540c785e2",
                "guest_count": 1,
                "subtotal": 28.0,
                "tax_total": 0.0,
                "open_time": "2024-06-25T15:25:49.589Z",
                "modified_time": "2024-06-25T15:25:49.589Z",
                "items": [
                    {
                        "line_id": "1",
                        "item_id": "008884303989M",
                        "quantity": 1,
                        "unit_price": 28.0,
                        "subtotal": 28.0,
                        "tax_included": 0
                    }
                ],
                "payments": [
                    {
                        "payment_id": "a522e41a-c3a9-4e10-a24a-a3d36e09f295",
                        "amount": 28.0,
                        "type": "Credit",
                        "payment_time": "2024-06-25T15:25:49.589Z",
                        "user_id": "32c462e4-3307-11ef-9c39-ef17ac110004",
                        "user_id_type": "External_ID"
                    }
                ],
                "discounts": [],
                "transaction_type": "QSR_SALE"
            }
        },
        "status": 200,
        "response": "{\"status\":\"OK\",\"payload\":null,\"errors\":null}"
    },
    {
        "request_body": {
            "store_id": "6A2FE030-08F8-44E0-842F-1D92A0874096",
            "client_id": "02B8E29F-7475-436F-94AA-D631E3577A28",
            "request_id": "ff7e07f2-134f-45d3-a181-b39194b6a744",
            "request_payload": {
                "is_closed": true,
                "is_voided": false,
                "channel": "IN-STORE",
                "pos_employee_id": "234234",
                "transaction_id": "7dbc4439-b97d-4a38-9458-e2e33121d8da",
                "guest_count": 1,
                "subtotal": 11.0,
                "tax_total": 0.0,
                "open_time": "2024-06-25T15:25:49.589Z",
                "modified_time": "2024-06-25T15:25:49.589Z",
                "items": [
                    {
                        "line_id": "1",
                        "item_id": "008884303989M",
                        "quantity": 1,
                        "unit_price": 11.0,
                        "subtotal": 11.0,
                        "tax_included": 0
                    }
                ],
                "payments": [
                    {
                        "payment_id": "605b9210-04ee-4024-84dc-91c9590c09ee",
                        "amount": 11.0,
                        "type": "Credit",
                        "payment_time": "2024-06-25T15:25:49.589Z",
                        "user_id": "32c55ac8-3307-11ef-8f1a-5d6aac110003",
                        "user_id_type": "External_ID"
                    }
                ],
                "discounts": [],
                "transaction_type": "QSR_SALE"
            }
        },
        "status": 200,
        "response": "{\"status\":\"OK\",\"payload\":null,\"errors\":null}"
    },
    {
        "request_body": {
            "store_id": "6A2FE030-08F8-44E0-842F-1D92A0874096",
            "client_id": "02B8E29F-7475-436F-94AA-D631E3577A28",
            "request_id": "8af29948-3c57-4421-aeba-355f41724b4f",
            "request_payload": {
                "is_closed": true,
                "is_voided": false,
                "channel": "MOBILE",
                "pos_employee_id": "234234",
                "transaction_id": "637a1f47-b0e6-42a2-9b5f-fde5c793988d",
                "guest_count": 1,
                "subtotal": 58.0,
                "tax_total": 0.0,
                "open_time": "2024-06-25T15:25:49.589Z",
                "modified_time": "2024-06-25T15:25:49.589Z",
                "items": [
                    {
                        "line_id": "1",
                        "item_id": "008884303989M",
                        "quantity": 1,
                        "unit_price": 58.0,
                        "subtotal": 58.0,
                        "tax_included": 0
                    }
                ],
                "payments": [
                    {
                        "payment_id": "5273d7d1-d17f-4803-ae5f-fd9936bd1e68",
                        "amount": 58.0,
                        "type": "Cash",
                        "payment_time": "2024-06-25T15:25:49.589Z",
                        "user_id": "32c4ec8c-3307-11ef-8e93-c349ac110005",
                        "user_id_type": "External_ID"
                    }
                ],
                "discounts": [],
                "transaction_type": "QSR_SALE"
            }
        },
        "status": 200,
        "response": "{\"status\":\"OK\",\"payload\":null,\"errors\":null}"
    },
    {
        "request_body": {
            "store_id": "6A2FE030-08F8-44E0-842F-1D92A0874096",
            "client_id": "02B8E29F-7475-436F-94AA-D631E3577A28",
            "request_id": "e0943436-cbed-4e7f-8fa6-64f6bd0906aa",
            "request_payload": {
                "is_closed": true,
                "is_voided": false,
                "channel": "MOBILE",
                "pos_employee_id": "234234",
                "transaction_id": "1c44f45e-c861-46ff-9ab2-ee19855eccc8",
                "guest_count": 1,
                "subtotal": 88.0,
                "tax_total": 0.0,
                "open_time": "2024-06-25T15:25:49.589Z",
                "modified_time": "2024-06-25T15:25:49.589Z",
                "items": [
                    {
                        "line_id": "1",
                        "item_id": "008884303989M",
                        "quantity": 1,
                        "unit_price": 88.0,
                        "subtotal": 88.0,
                        "tax_included": 0
                    }
                ],
                "payments": [
                    {
                        "payment_id": "ebe4ac75-8ff5-4e0b-bb77-77c330605389",
                        "amount": 88.0,
                        "type": "Gift Card",
                        "payment_time": "2024-06-25T15:25:49.589Z",
                        "user_id": "32c57396-3307-11ef-822c-facdac110006",
                        "user_id_type": "External_ID"
                    }
                ],
                "discounts": [],
                "transaction_type": "QSR_SALE"
            }
        },
        "status": 200,
        "response": "{\"status\":\"OK\",\"payload\":null,\"errors\":null}"
    },
    {
        "request_body": {
            "store_id": "6A2FE030-08F8-44E0-842F-1D92A0874096",
            "client_id": "02B8E29F-7475-436F-94AA-D631E3577A28",
            "request_id": "79b21e9c-f8a7-42bb-989f-c74ecd8c5e92",
            "request_payload": {
                "is_closed": true,
                "is_voided": false,
                "channel": "IN-STORE",
                "pos_employee_id": "234234",
                "transaction_id": "2ec529dd-2362-4d45-af38-021a1089053b",
                "guest_count": 1,
                "subtotal": 76.0,
                "tax_total": 0.0,
                "open_time": "2024-06-25T15:25:49.590Z",
                "modified_time": "2024-06-25T15:25:49.590Z",
                "items": [
                    {
                        "line_id": "1",
                        "item_id": "008884303989M",
                        "quantity": 1,
                        "unit_price": 76.0,
                        "subtotal": 76.0,
                        "tax_included": 0
                    }
                ],
                "payments": [
                    {
                        "payment_id": "e54d07c2-f1c9-4964-aa21-8956bd06d9e4",
                        "amount": 76.0,
                        "type": "Gift Card",
                        "payment_time": "2024-06-25T15:25:49.590Z",
                        "user_id": "32c460c8-3307-11ef-80bf-6b95ac110003",
                        "user_id_type": "External_ID"
                    }
                ],
                "discounts": [],
                "transaction_type": "QSR_SALE"
            }
        },
        "status": 200,
        "response": "{\"status\":\"OK\",\"payload\":null,\"errors\":null}"
    },
    {
        "request_body": {
            "store_id": "6A2FE030-08F8-44E0-842F-1D92A0874096",
            "client_id": "02B8E29F-7475-436F-94AA-D631E3577A28",
            "request_id": "df7dd5d4-813d-44b6-84db-2b7d8dd2d1de",
            "request_payload": {
                "is_closed": true,
                "is_voided": false,
                "channel": "MOBILE",
                "pos_employee_id": "234234",
                "transaction_id": "ce385f7b-9912-4944-8170-5a24997fe3c3",
                "guest_count": 1,
                "subtotal": 78.0,
                "tax_total": 0.0,
                "open_time": "2024-06-25T15:25:49.590Z",
                "modified_time": "2024-06-25T15:25:49.590Z",
                "items": [
                    {
                        "line_id": "1",
                        "item_id": "008884303989M",
                        "quantity": 1,
                        "unit_price": 78.0,
                        "subtotal": 78.0,
                        "tax_included": 0
                    }
                ],
                "payments": [
                    {
                        "payment_id": "1e2a75ed-9dd3-4c92-be17-61013069160e",
                        "amount": 78.0,
                        "type": "Cash",
                        "payment_time": "2024-06-25T15:25:49.590Z",
                        "user_id": "32c53fa2-3307-11ef-99fc-984eac110004",
                        "user_id_type": "External_ID"
                    }
                ],
                "discounts": [],
                "transaction_type": "QSR_SALE"
            }
        },
        "status": 200,
        "response": "{\"status\":\"OK\",\"payload\":null,\"errors\":null}"
    },
    {
        "request_body": {
            "store_id": "6A2FE030-08F8-44E0-842F-1D92A0874096",
            "client_id": "02B8E29F-7475-436F-94AA-D631E3577A28",
            "request_id": "eb40add5-3530-4e23-bb18-4e8a374c734a",
            "request_payload": {
                "is_closed": true,
                "is_voided": false,
                "channel": "MOBILE",
                "pos_employee_id": "234234",
                "transaction_id": "b0341519-fb9f-4a05-bf44-2978356ebd1d",
                "guest_count": 1,
                "subtotal": 19.0,
                "tax_total": 0.0,
                "open_time": "2024-06-25T15:25:49.590Z",
                "modified_time": "2024-06-25T15:25:49.590Z",
                "items": [
                    {
                        "line_id": "1",
                        "item_id": "008884303989M",
                        "quantity": 1,
                        "unit_price": 19.0,
                        "subtotal": 19.0,
                        "tax_included": 0
                    }
                ],
                "payments": [
                    {
                        "payment_id": "df8272df-8d2e-43b2-93b4-2fef37b58381",
                        "amount": 19.0,
                        "type": "Cash",
                        "payment_time": "2024-06-25T15:25:49.590Z",
                        "user_id": "32c4ee58-3307-11ef-8996-7279ac110005",
                        "user_id_type": "External_ID"
                    }
                ],
                "discounts": [],
                "transaction_type": "QSR_SALE"
            }
        },
        "status": 500,
        "response": ""
    },
    {
        "request_body": {
            "store_id": "6A2FE030-08F8-44E0-842F-1D92A0874096",
            "client_id": "02B8E29F-7475-436F-94AA-D631E3577A28",
            "request_id": "d76cfbb9-cbff-4e6b-982e-918f5c228d15",
            "request_payload": {
                "is_closed": true,
                "is_voided": false,
                "channel": "IN-STORE",
                "pos_employee_id": "234234",
                "transaction_id": "59665724-c0ac-42d9-a9a8-40c35b492e1f",
                "guest_count": 1,
                "subtotal": 51.0,
                "tax_total": 0.0,
                "open_time": "2024-06-25T15:25:49.590Z",
                "modified_time": "2024-06-25T15:25:49.590Z",
                "items": [
                    {
                        "line_id": "1",
                        "item_id": "008884303989M",
                        "quantity": 1,
                        "unit_price": 51.0,
                        "subtotal": 51.0,
                        "tax_included": 0
                    }
                ],
                "payments": [
                    {
                        "payment_id": "143e1d9e-54fb-4438-8146-9c057c62a696",
                        "amount": 51.0,
                        "type": "Cash",
                        "payment_time": "2024-06-25T15:25:49.590Z",
                        "user_id": "32c4de36-3307-11ef-96e1-b0bdac110003",
                        "user_id_type": "External_ID"
                    }
                ],
                "discounts": [],
                "transaction_type": "QSR_SALE"
            }
        },
        "status": 200,
        "response": "{\"status\":\"OK\",\"payload\":null,\"errors\":null}"
    },
    {
        "request_body": {
            "store_id": "6A2FE030-08F8-44E0-842F-1D92A0874096",
            "client_id": "02B8E29F-7475-436F-94AA-D631E3577A28",
            "request_id": "efc2c7eb-2274-4550-9029-d501e519d5a3",
            "request_payload": {
                "is_closed": true,
                "is_voided": false,
                "channel": "MOBILE",
                "pos_employee_id": "234234",
                "transaction_id": "0332425b-ba1a-4d82-adc3-6ea84e005f85",
                "guest_count": 1,
                "subtotal": 98.0,
                "tax_total": 0.0,
                "open_time": "2024-06-25T15:25:49.590Z",
                "modified_time": "2024-06-25T15:25:49.590Z",
                "items": [
                    {
                        "line_id": "1",
                        "item_id": "008884303989M",
                        "quantity": 1,
                        "unit_price": 98.0,
                        "subtotal": 98.0,
                        "tax_included": 0
                    }
                ],
                "payments": [
                    {
                        "payment_id": "854f6656-9162-47de-97a9-4c6503f94698",
                        "amount": 98.0,
                        "type": "Gift Card",
                        "payment_time": "2024-06-25T15:25:49.590Z",
                        "user_id": "32c546be-3307-11ef-8f7c-a177ac110003",
                        "user_id_type": "External_ID"
                    }
                ],
                "discounts": [],
                "transaction_type": "QSR_SALE"
            }
        },
        "status": 500,
        "response": ""
    },
    {
        "request_body": {
            "store_id": "6A2FE030-08F8-44E0-842F-1D92A0874096",
            "client_id": "02B8E29F-7475-436F-94AA-D631E3577A28",
            "request_id": "fa86f185-dac8-4622-9d6d-c8085912b3e3",
            "request_payload": {
                "is_closed": true,
                "is_voided": false,
                "channel": "MOBILE",
                "pos_employee_id": "234234",
                "transaction_id": "65f685b4-074d-4ed3-94d1-af8482224147",
                "guest_count": 1,
                "subtotal": 76.0,
                "tax_total": 0.0,
                "open_time": "2024-06-25T15:25:49.590Z",
                "modified_time": "2024-06-25T15:25:49.590Z",
                "items": [
                    {
                        "line_id": "1",
                        "item_id": "008884303989M",
                        "quantity": 1,
                        "unit_price": 76.0,
                        "subtotal": 76.0,
                        "tax_included": 0
                    }
                ],
                "payments": [
                    {
                        "payment_id": "3fd34d68-853b-4e81-a3f3-0e01c37f00a0",
                        "amount": 76.0,
                        "type": "Gift Card",
                        "payment_time": "2024-06-25T15:25:49.590Z",
                        "user_id": "32c6a626-3307-11ef-9a5c-a5b9ac110003",
                        "user_id_type": "External_ID"
                    }
                ],
                "discounts": [],
                "transaction_type": "QSR_SALE"
            }
        },
        "status": 200,
        "response": "{\"status\":\"OK\",\"payload\":null,\"errors\":null}"
    },
    {
        "request_body": {
            "store_id": "6A2FE030-08F8-44E0-842F-1D92A0874096",
            "client_id": "02B8E29F-7475-436F-94AA-D631E3577A28",
            "request_id": "4a29fcdc-509b-43f8-a16c-2096a34c2525",
            "request_payload": {
                "is_closed": true,
                "is_voided": false,
                "channel": "MOBILE",
                "pos_employee_id": "234234",
                "transaction_id": "5dfaff62-9b5d-44af-b626-6f72ee97bb35",
                "guest_count": 1,
                "subtotal": 19.0,
                "tax_total": 0.0,
                "open_time": "2024-06-25T15:25:49.590Z",
                "modified_time": "2024-06-25T15:25:49.590Z",
                "items": [
                    {
                        "line_id": "1",
                        "item_id": "008884303989M",
                        "quantity": 1,
                        "unit_price": 19.0,
                        "subtotal": 19.0,
                        "tax_included": 0
                    }
                ],
                "payments": [
                    {
                        "payment_id": "ff96fc57-4498-4d22-b7f8-61f1bbaaaf6d",
                        "amount": 19.0,
                        "type": "Credit",
                        "payment_time": "2024-06-25T15:25:49.590Z",
                        "user_id": "32c3be48-3307-11ef-90bc-d62aac110003",
                        "user_id_type": "External_ID"
                    }
                ],
                "discounts": [],
                "transaction_type": "QSR_SALE"
            }
        },
        "status": 200,
        "response": "{\"status\":\"OK\",\"payload\":null,\"errors\":null}"
    },
    {
        "request_body": {
            "store_id": "6A2FE030-08F8-44E0-842F-1D92A0874096",
            "client_id": "02B8E29F-7475-436F-94AA-D631E3577A28",
            "request_id": "4947745e-6c33-4bdb-b3df-7ff0749a4831",
            "request_payload": {
                "is_closed": true,
                "is_voided": false,
                "channel": "IN-STORE",
                "pos_employee_id": "234234",
                "transaction_id": "8eb81ee9-8aff-433d-9b53-276d0c09a20d",
                "guest_count": 1,
                "subtotal": 51.0,
                "tax_total": 0.0,
                "open_time": "2024-06-25T15:25:49.590Z",
                "modified_time": "2024-06-25T15:25:49.590Z",
                "items": [
                    {
                        "line_id": "1",
                        "item_id": "008884303989M",
                        "quantity": 1,
                        "unit_price": 51.0,
                        "subtotal": 51.0,
                        "tax_included": 0
                    }
                ],
                "payments": [
                    {
                        "payment_id": "213ff73c-93db-4931-b81b-5c312dd4ff5a",
                        "amount": 51.0,
                        "type": "Gift Card",
                        "payment_time": "2024-06-25T15:25:49.590Z",
                        "user_id": "32c0a7bc-3307-11ef-8c91-2a5eac110003",
                        "user_id_type": "External_ID"
                    }
                ],
                "discounts": [],
                "transaction_type": "QSR_SALE"
            }
        },
        "status": 500,
        "response": ""
    },
    {
        "request_body": {
            "store_id": "6A2FE030-08F8-44E0-842F-1D92A0874096",
            "client_id": "02B8E29F-7475-436F-94AA-D631E3577A28",
            "request_id": "43774109-8820-4ad0-82c7-9adcc503eabf",
            "request_payload": {
                "is_closed": true,
                "is_voided": false,
                "channel": "MOBILE",
                "pos_employee_id": "234234",
                "transaction_id": "ebf936ad-f956-4c6c-be0b-f1cdc321b829",
                "guest_count": 1,
                "subtotal": 80.0,
                "tax_total": 0.0,
                "open_time": "2024-06-25T15:25:49.590Z",
                "modified_time": "2024-06-25T15:25:49.590Z",
                "items": [
                    {
                        "line_id": "1",
                        "item_id": "008884303989M",
                        "quantity": 1,
                        "unit_price": 80.0,
                        "subtotal": 80.0,
                        "tax_included": 0
                    }
                ],
                "payments": [
                    {
                        "payment_id": "10d38779-bb37-4ea1-add2-dc348e1d7062",
                        "amount": 80.0,
                        "type": "Credit",
                        "payment_time": "2024-06-25T15:25:49.590Z",
                        "user_id": "32c678b8-3307-11ef-9817-c92fac110004",
                        "user_id_type": "External_ID"
                    }
                ],
                "discounts": [],
                "transaction_type": "QSR_SALE"
            }
        },
        "status": 200,
        "response": "{\"status\":\"OK\",\"payload\":null,\"errors\":null}"
    },
    {
        "request_body": {
            "store_id": "6A2FE030-08F8-44E0-842F-1D92A0874096",
            "client_id": "02B8E29F-7475-436F-94AA-D631E3577A28",
            "request_id": "14991e85-c9ff-46be-b923-0d6858f556e8",
            "request_payload": {
                "is_closed": true,
                "is_voided": false,
                "channel": "IN-STORE",
                "pos_employee_id": "234234",
                "transaction_id": "c231d007-19da-4b33-8913-355d4a9141cd",
                "guest_count": 1,
                "subtotal": 51.0,
                "tax_total": 0.0,
                "open_time": "2024-06-25T15:25:49.590Z",
                "modified_time": "2024-06-25T15:25:49.590Z",
                "items": [
                    {
                        "line_id": "1",
                        "item_id": "008884303989M",
                        "quantity": 1,
                        "unit_price": 51.0,
                        "subtotal": 51.0,
                        "tax_included": 0
                    }
                ],
                "payments": [
                    {
                        "payment_id": "203e5a23-1288-4920-ab95-f0989c957dd3",
                        "amount": 51.0,
                        "type": "Gift Card",
                        "payment_time": "2024-06-25T15:25:49.590Z",
                        "user_id": "32c72e66-3307-11ef-90eb-ef4cac110003",
                        "user_id_type": "External_ID"
                    }
                ],
                "discounts": [],
                "transaction_type": "QSR_SALE"
            }
        },
        "status": 500,
        "response": ""
    },
    {
        "request_body": {
            "store_id": "6A2FE030-08F8-44E0-842F-1D92A0874096",
            "client_id": "02B8E29F-7475-436F-94AA-D631E3577A28",
            "request_id": "fc2aaa40-42bd-4011-bfc2-31e236e6b3ce",
            "request_payload": {
                "is_closed": true,
                "is_voided": false,
                "channel": "MOBILE",
                "pos_employee_id": "234234",
                "transaction_id": "fe3b4b4a-8b77-4ca0-b583-7bcacdc3da17",
                "guest_count": 1,
                "subtotal": 88.0,
                "tax_total": 0.0,
                "open_time": "2024-06-25T15:25:49.590Z",
                "modified_time": "2024-06-25T15:25:49.590Z",
                "items": [
                    {
                        "line_id": "1",
                        "item_id": "008884303989M",
                        "quantity": 1,
                        "unit_price": 88.0,
                        "subtotal": 88.0,
                        "tax_included": 0
                    }
                ],
                "payments": [
                    {
                        "payment_id": "22ab3664-bfaa-42a8-a259-c40272ce0848",
                        "amount": 88.0,
                        "type": "Cash",
                        "payment_time": "2024-06-25T15:25:49.590Z",
                        "user_id": "32c5b59a-3307-11ef-9aa2-d8d1ac110006",
                        "user_id_type": "External_ID"
                    }
                ],
                "discounts": [],
                "transaction_type": "QSR_SALE"
            }
        },
        "status": 200,
        "response": "{\"status\":\"OK\",\"payload\":null,\"errors\":null}"
    },
    {
        "request_body": {
            "store_id": "6A2FE030-08F8-44E0-842F-1D92A0874096",
            "client_id": "02B8E29F-7475-436F-94AA-D631E3577A28",
            "request_id": "a6fed884-6da3-420d-9072-be2b04070461",
            "request_payload": {
                "is_closed": true,
                "is_voided": false,
                "channel": "IN-STORE",
                "pos_employee_id": "234234",
                "transaction_id": "2f905941-4876-4ce0-9f58-6a9e359afb79",
                "guest_count": 1,
                "subtotal": 15.0,
                "tax_total": 0.0,
                "open_time": "2024-06-25T15:25:49.590Z",
                "modified_time": "2024-06-25T15:25:49.590Z",
                "items": [
                    {
                        "line_id": "1",
                        "item_id": "008884303989M",
                        "quantity": 1,
                        "unit_price": 15.0,
                        "subtotal": 15.0,
                        "tax_included": 0
                    }
                ],
                "payments": [
                    {
                        "payment_id": "3c23f08e-4937-48f5-bdae-4b048611c9cc",
                        "amount": 15.0,
                        "type": "Gift Card",
                        "payment_time": "2024-06-25T15:25:49.590Z",
                        "user_id": "32c73b36-3307-11ef-8523-cce3ac110003",
                        "user_id_type": "External_ID"
                    }
                ],
                "discounts": [],
                "transaction_type": "QSR_SALE"
            }
        },
        "status": 200,
        "response": "{\"status\":\"OK\",\"payload\":null,\"errors\":null}"
    },
    {
        "request_body": {
            "store_id": "6A2FE030-08F8-44E0-842F-1D92A0874096",
            "client_id": "02B8E29F-7475-436F-94AA-D631E3577A28",
            "request_id": "e98b2246-6d8e-4586-8d02-cb2e88b2b7e5",
            "request_payload": {
                "is_closed": true,
                "is_voided": false,
                "channel": "IN-STORE",
                "pos_employee_id": "234234",
                "transaction_id": "07cc1fa3-0ead-4960-8f48-46a7ef288dcd",
                "guest_count": 1,
                "subtotal": 55.0,
                "tax_total": 0.0,
                "open_time": "2024-06-25T15:25:49.590Z",
                "modified_time": "2024-06-25T15:25:49.590Z",
                "items": [
                    {
                        "line_id": "1",
                        "item_id": "008884303989M",
                        "quantity": 1,
                        "unit_price": 55.0,
                        "subtotal": 55.0,
                        "tax_included": 0
                    }
                ],
                "payments": [
                    {
                        "payment_id": "838c1c36-7662-4a97-9205-ec092a535241",
                        "amount": 55.0,
                        "type": "Gift Card",
                        "payment_time": "2024-06-25T15:25:49.590Z",
                        "user_id": "32c4b01e-3307-11ef-9907-6ac1ac110005",
                        "user_id_type": "External_ID"
                    }
                ],
                "discounts": [],
                "transaction_type": "QSR_SALE"
            }
        },
        "status": 500,
        "response": ""
    },
    {
        "request_body": {
            "store_id": "6A2FE030-08F8-44E0-842F-1D92A0874096",
            "client_id": "02B8E29F-7475-436F-94AA-D631E3577A28",
            "request_id": "4f5f84eb-154e-4a6a-b23f-ba3e7b66bceb",
            "request_payload": {
                "is_closed": true,
                "is_voided": false,
                "channel": "MOBILE",
                "pos_employee_id": "234234",
                "transaction_id": "6ec0b218-cacf-4bbe-8054-b230a22cd435",
                "guest_count": 1,
                "subtotal": 89.0,
                "tax_total": 0.0,
                "open_time": "2024-06-25T15:25:49.590Z",
                "modified_time": "2024-06-25T15:25:49.590Z",
                "items": [
                    {
                        "line_id": "1",
                        "item_id": "008884303989M",
                        "quantity": 1,
                        "unit_price": 89.0,
                        "subtotal": 89.0,
                        "tax_included": 0
                    }
                ],
                "payments": [
                    {
                        "payment_id": "5eabb815-9bbb-467d-8f7d-cd914e5fb780",
                        "amount": 89.0,
                        "type": "Gift Card",
                        "payment_time": "2024-06-25T15:25:49.590Z",
                        "user_id": "32c594d4-3307-11ef-8651-940bac110004",
                        "user_id_type": "External_ID"
                    }
                ],
                "discounts": [],
                "transaction_type": "QSR_SALE"
            }
        },
        "status": 200,
        "response": "{\"status\":\"OK\",\"payload\":null,\"errors\":null}"
    },
    {
        "request_body": {
            "store_id": "6A2FE030-08F8-44E0-842F-1D92A0874096",
            "client_id": "02B8E29F-7475-436F-94AA-D631E3577A28",
            "request_id": "0952da22-39a7-44f5-b41e-bd0e59e3e14b",
            "request_payload": {
                "is_closed": true,
                "is_voided": false,
                "channel": "IN-STORE",
                "pos_employee_id": "234234",
                "transaction_id": "a8716dd9-34fd-4be4-b91a-d85695f832a9",
                "guest_count": 1,
                "subtotal": 51.0,
                "tax_total": 0.0,
                "open_time": "2024-06-25T15:25:49.590Z",
                "modified_time": "2024-06-25T15:25:49.590Z",
                "items": [
                    {
                        "line_id": "1",
                        "item_id": "008884303989M",
                        "quantity": 1,
                        "unit_price": 51.0,
                        "subtotal": 51.0,
                        "tax_included": 0
                    }
                ],
                "payments": [
                    {
                        "payment_id": "79cdaaa8-6856-425f-9905-930e41c90384",
                        "amount": 51.0,
                        "type": "Gift Card",
                        "payment_time": "2024-06-25T15:25:49.590Z",
                        "user_id": "32c58df4-3307-11ef-9fb4-3032ac110004",
                        "user_id_type": "External_ID"
                    }
                ],
                "discounts": [],
                "transaction_type": "QSR_SALE"
            }
        },
        "status": 500,
        "response": ""
    }
]